tigrmail/__init__.py
tigrmail/api.py
tigrmail/client.py
tigrmail/errors.py
tigrmail-0.4.0.dist-info/METADATA
tigrmail-0.4.0.dist-info/WHEEL
tigrmail-0.4.0.dist-info/licenses/LICENCE
tigrmail-0.4.0.dist-info/RECORD
