Metadata-Version: 2.4
Name: tigrmail
Version: 0.4.0
Summary: API client for creating temporary email addresses to use in your E2E tests with Playwright, Cypress, and other frameworks.
Project-URL: Homepage, https://tigrmail.com
Project-URL: Documentation, https://docs.tigrmail.com
Project-URL: Repository, https://github.com/furionix-labs/tigrmail-python
Author: Furionix Labs
License-Expression: MIT
License-File: LICENCE
Requires-Python: >=3.8
Requires-Dist: httpx<0.29,>=0.24
Requires-Dist: typing-extensions>=4.0.0
